{
  "common": {
    "siteName": "올인원 툴허브",
    "siteDescription": "한국과 일본을 위한 고성능 SEO 최적화 도구 플랫폼",
    "language": "한국어",
    "switchLanguage": "언어 전환",
    "home": "홈",
    "tools": "도구",
    "categories": "카테고리",
    "search": "검색",
    "searchPlaceholder": "도구 검색...",
    "featuredTools": "추천 도구",
    "allTools": "모든 도구",
    "recentTools": "최근 도구",
    "popularTools": "인기 도구",
    "developerTools": "개발자 도구",
    "textTools": "텍스트 도구",
    "imageTools": "이미지 도구",
    "pdfTools": "PDF 도구",
    "converterTools": "변환기 도구",
    "seoTools": "SEO 도구",
    "tryNow": "지금 사용해보기",
    "freeToUse": "무료 사용",
    "noRegistration": "회원가입 불필요",
    "instantResults": "즉시 결과",
    "advertisement": "광고",
    "loading": "로딩 중...",
    "error": "오류 발생",
    "retry": "다시 시도",
    "copy": "복사",
    "download": "다운로드",
    "upload": "업로드",
    "clear": "지우기",
    "submit": "제출",
    "cancel": "취소",
    "success": "성공",
    "failed": "실패"
  },
  "categories": {
    "text": "텍스트",
    "image": "이미지",
    "pdf": "PDF",
    "converter": "변환기",
    "developer": "개발자",
    "seo": "SEO"
  },
  "footer": {
    "description": "한국과 일본 사용자를 위한 고성능 웹 도구 플랫폼",
    "quickLinks": "빠른 링크",
    "categories": "카테고리",
    "legal": "법적 정보",
    "privacyPolicy": "개인정보 처리방침",
    "termsOfService": "이용약관",
    "contact": "문의하기",
    "copyright": "© 2025 올인원 툴허브. 모든 권리 보유.",
    "madeWith": "로 제작됨",
    "in": "에서"
  },
  "seo": {
    "homeTitle": "올인원 툴허브 - 한국/일본 무료 웹 도구 모음",
    "homeDescription": "텍스트 카운터, PDF 병합, 이미지 압축, JSON 포맷터 등 다양한 무료 웹 도구를 제공합니다. 회원가입 없이 즉시 사용 가능!",
    "toolsTitle": "모든 도구 - 올인원 툴허브",
    "toolsDescription": "카테고리별로 정리된 모든 웹 도구를 확인해보세요. 텍스트, 이미지, PDF, 개발자 도구 등 다양한 유틸리티 제공"
  }
}
